hillslopetoy/__init__.py
hillslopetoy/cli.py
hillslopetoy/hillslopetoy.py
hillslopetoy-0.1.0.dist-info/AUTHORS.rst
hillslopetoy-0.1.0.dist-info/LICENSE
hillslopetoy-0.1.0.dist-info/METADATA
hillslopetoy-0.1.0.dist-info/WHEEL
hillslopetoy-0.1.0.dist-info/entry_points.txt
hillslopetoy-0.1.0.dist-info/top_level.txt
hillslopetoy-0.1.0.dist-info/RECORD
