Metadata-Version: 2.1
Name: hillslopetoy
Version: 0.1.0
Summary: A collection of tools for exploring hillslope evolution.
Home-page: https://github.com/simon-m-mudd/hillslopetoy
Author: Simon M Mudd
Author-email: simon.m.mudd@ed.ac.uk
License: MIT license
Keywords: hillslopetoy
Classifier: Development Status :: 2 - Pre-Alpha
Classifier: Intended Audience :: Developers
Classifier: License :: OSI Approved :: MIT License
Classifier: Natural Language :: English
Classifier: Programming Language :: Python :: 3
Classifier: Programming Language :: Python :: 3.6
Classifier: Programming Language :: Python :: 3.7
Classifier: Programming Language :: Python :: 3.8
Classifier: Programming Language :: Python :: 3.9
Classifier: Programming Language :: Python :: 3.10
Requires-Python: >=3.5
License-File: LICENSE
License-File: AUTHORS.rst
Requires-Dist: Click (>=7.0)
